README.rst
setup.py
validatorchain.py
django_validatorchain.egg-info/PKG-INFO
django_validatorchain.egg-info/SOURCES.txt
django_validatorchain.egg-info/dependency_links.txt
django_validatorchain.egg-info/top_level.txt