Metadata-Version: 1.0
Name: django-validatorchain
Version: 0.1
Summary: Helper for making form validators skippable
Home-page: https://github.com/zerok/django-validatorchain
Author: Horst Gutmann
Author-email: horst@zerokspot.com
License: BSD
Platform: UNKNOWN
